{"nodes": [{"id": "c_users_erdem_mert_yolcu_desktop_bist_terminal_project_src_components_aiadvisor_scanhistorydrawer_jsx", "label": "ScanHistoryDrawer.jsx", "file_type": "code", "source_file": "C:\\Users\\Erdem Mert Yolcu\\Desktop\\bist-terminal-project\\src\\components\\AIAdvisor\\ScanHistoryDrawer.jsx", "source_location": "L1"}, {"id": "scanhistorydrawer_scanhistorydrawer", "label": "ScanHistoryDrawer()", "file_type": "code", "source_file": "C:\\Users\\Erdem Mert Yolcu\\Desktop\\bist-terminal-project\\src\\components\\AIAdvisor\\ScanHistoryDrawer.jsx", "source_location": "L3"}], "edges": [{"source": "c_users_erdem_mert_yolcu_desktop_bist_terminal_project_src_components_aiadvisor_scanhistorydrawer_jsx", "target": "react", "relation": "imports_from", "confidence": "EXTRACTED", "source_file": "C:\\Users\\Erdem Mert Yolcu\\Desktop\\bist-terminal-project\\src\\components\\AIAdvisor\\ScanHistoryDrawer.jsx", "source_location": "L1", "weight": 1.0}, {"source": "c_users_erdem_mert_yolcu_desktop_bist_terminal_project_src_components_aiadvisor_scanhistorydrawer_jsx", "target": "scanhistorydrawer_scanhistorydrawer", "relation": "contains", "confidence": "EXTRACTED", "source_file": "C:\\Users\\Erdem Mert Yolcu\\Desktop\\bist-terminal-project\\src\\components\\AIAdvisor\\ScanHistoryDrawer.jsx", "source_location": "L3", "weight": 1.0}], "raw_calls": [{"caller_nid": "scanhistorydrawer_scanhistorydrawer", "callee": "useState", "source_file": "C:\\Users\\Erdem Mert Yolcu\\Desktop\\bist-terminal-project\\src\\components\\AIAdvisor\\ScanHistoryDrawer.jsx", "source_location": "L4"}, {"caller_nid": "scanhistorydrawer_scanhistorydrawer", "callee": "slice", "source_file": "C:\\Users\\Erdem Mert Yolcu\\Desktop\\bist-terminal-project\\src\\components\\AIAdvisor\\ScanHistoryDrawer.jsx", "source_location": "L7"}, {"caller_nid": "scanhistorydrawer_scanhistorydrawer", "callee": "sort", "source_file": "C:\\Users\\Erdem Mert Yolcu\\Desktop\\bist-terminal-project\\src\\components\\AIAdvisor\\ScanHistoryDrawer.jsx", "source_location": "L7"}, {"caller_nid": "scanhistorydrawer_scanhistorydrawer", "callee": "map", "source_file": "C:\\Users\\Erdem Mert Yolcu\\Desktop\\bist-terminal-project\\src\\components\\AIAdvisor\\ScanHistoryDrawer.jsx", "source_location": "L156"}]}